naver_api/__init__.py
naver_api/naver_search.py
water/__init__.py
water/chosun.py
water/hani.py
water/kofiabond.py
water/naver.py
water/naver_search.py
water_api-0.6.dist-info/DESCRIPTION.rst
water_api-0.6.dist-info/METADATA
water_api-0.6.dist-info/RECORD
water_api-0.6.dist-info/WHEEL
water_api-0.6.dist-info/metadata.json
water_api-0.6.dist-info/top_level.txt
