Metadata-Version: 2.0
Name: water-api
Version: 0.6
Summary: A general container of apis out of Naver, Kakao
Home-page: https://github.com/harry81/naver_api
Author: Hyunmin Choi
Author-email: pointer81@gmail.com
License: MIT
Platform: UNKNOWN
Requires-Dist: bs4
Requires-Dist: requests
